<annotation>
	<folder>imageGenerate</folder>
	<filename>0_0_4083.jpg</filename>
	<path>C:\logo\imageGenerate\0_0_4083.jpg</path>
	<source>
		<database>Unknown</database>
	</source>
	<size>
		<width>200</width>
		<height>150</height>
		<depth>3</depth>
	</size>
	<segmented>0</segmented>
	<object>
		<name>nike</name>
		<pose>Unspecified</pose>
		<truncated>0</truncated>
		<difficult>0</difficult>
		<bndbox>
			<xmin>134</xmin>
			<ymin>72</ymin>
			<xmax>180</xmax>
			<ymax>123</ymax>
		</bndbox>
	</object>
	<object>
		<name>nike</name>
		<pose>Unspecified</pose>
		<truncated>1</truncated>
		<difficult>0</difficult>
		<bndbox>
			<xmin>72</xmin>
			<ymin>1</ymin>
			<xmax>108</xmax>
			<ymax>29</ymax>
		</bndbox>
	</object>
</annotation>
