<annotation>
	<folder>imageGenerate</folder>
	<filename>0_0_6800.jpg</filename>
	<path>C:\logo\imageGenerate\0_0_6800.jpg</path>
	<source>
		<database>Unknown</database>
	</source>
	<size>
		<width>200</width>
		<height>150</height>
		<depth>3</depth>
	</size>
	<segmented>0</segmented>
	<object>
		<name>nike</name>
		<pose>Unspecified</pose>
		<truncated>0</truncated>
		<difficult>0</difficult>
		<bndbox>
			<xmin>16</xmin>
			<ymin>71</ymin>
			<xmax>73</xmax>
			<ymax>91</ymax>
		</bndbox>
	</object>
	<object>
		<name>nike</name>
		<pose>Unspecified</pose>
		<truncated>0</truncated>
		<difficult>0</difficult>
		<bndbox>
			<xmin>120</xmin>
			<ymin>32</ymin>
			<xmax>170</xmax>
			<ymax>56</ymax>
		</bndbox>
	</object>
</annotation>
