<annotation>
	<folder>imageGenerate</folder>
	<filename>100_0_7454.jpg</filename>
	<path>C:\logo\imageGenerate\100_0_7454.jpg</path>
	<source>
		<database>Unknown</database>
	</source>
	<size>
		<width>200</width>
		<height>150</height>
		<depth>3</depth>
	</size>
	<segmented>0</segmented>
	<object>
		<name>apple</name>
		<pose>Unspecified</pose>
		<truncated>0</truncated>
		<difficult>0</difficult>
		<bndbox>
			<xmin>108</xmin>
			<ymin>39</ymin>
			<xmax>134</xmax>
			<ymax>69</ymax>
		</bndbox>
	</object>
</annotation>
